.DS_Store
.coveragerc
.gitignore
.isort.cfg
.pre-commit-config.yaml
.readthedocs.yml
.travis.yml
AUTHORS.rst
CHANGELOG.rst
CONTRIBUTING.rst
LICENSE
LICENSE.txt
MANIFEST.in
Makefile
README.rst
pyproject.toml
requirements.txt
setup.cfg
setup.py
tox.ini
conda/conda-environment.yaml
conda/conda-requirements.txt
conda/pip-requirements.txt
dev/develop.sh
dev/latest.txt
dev/prep-linux.sh
dev/push.sh
dev/requirements.txt
docker/server/Dockerfile
docker/server/Makefile
docker/server/README.md
docker/server/build_metatab.sh
docker/server/compose.yaml
docker/server/environment-private.template.env
docker/server/metapack-template.yaml
docker/test/Dockerfile
docker/test/Makefile
docker/test/setup-git.sh
docker/test/setup-pip.sh
docs/.buildinfo
docs/.nojekyll
docs/CNAME
docs/Makefile
docs/authors.rst
docs/changelog.rst
docs/commands.html
docs/conf.py
docs/contributing.rst
docs/genindex.html
docs/index.html
docs/index.rst
docs/license.rst
docs/objects.inv
docs/overview.html
docs/readme.rst
docs/requirements.txt
docs/search.html
docs/searchindex.js
docs/using.html
docs/_sources/commands.rst.txt
docs/_sources/index.rst.txt
docs/_sources/overview.rst.txt
docs/_sources/using.rst.txt
examples/Metatab Package.ipynb
examples/Pandas Reporter Example.ipynb
examples/pandas-reporter.py
sphinx/Makefile
sphinx/make.bat
sphinx/requirements.txt
sphinx/source/commands.rst
sphinx/source/conf.py
sphinx/source/index.rst
sphinx/source/overview.rst
sphinx/source/using.rst
sphinx/source/code/open.py
src/metapack/__init__.py
src/metapack/appurl.py
src/metapack/categorical.py
src/metapack/constants.py
src/metapack/doc.py
src/metapack/env.py
src/metapack/exc.py
src/metapack/html.py
src/metapack/index.py
src/metapack/jupyter.py
src/metapack/package.py
src/metapack/terms.py
src/metapack/util.py
src/metapack.egg-info/PKG-INFO
src/metapack.egg-info/SOURCES.txt
src/metapack.egg-info/dependency_links.txt
src/metapack.egg-info/entry_points.txt
src/metapack.egg-info/not-zip-safe
src/metapack.egg-info/requires.txt
src/metapack.egg-info/top_level.txt
src/metapack/cli/__init__.py
src/metapack/cli/config.py
src/metapack/cli/core.py
src/metapack/cli/doc.py
src/metapack/cli/index.py
src/metapack/cli/info.py
src/metapack/cli/mp.py
src/metapack/cli/open.py
