Metadata-Version: 2.1
Name: metapack
Version: 0.9.36
Summary: Parse and manipulate structured data and metadata in a tabular format.
Home-page: https://pyscaffold.org/
Author: Eric Busboom
Author-email: eric@civicknowledge.com
License: mit
Platform: any
Classifier: Development Status :: 4 - Beta
Classifier: Programming Language :: Python
Provides-Extra: testing
License-File: LICENSE
License-File: LICENSE.txt
License-File: AUTHORS.rst
